omfvtk/__init__.py
omfvtk/lineset.py
omfvtk/pointset.py
omfvtk/surface.py
omfvtk/volume.py
omfvtk/wrapper.py
omfvtk-0.0.0.dist-info/METADATA
omfvtk-0.0.0.dist-info/RECORD
omfvtk-0.0.0.dist-info/WHEEL
omfvtk-0.0.0.dist-info/top_level.txt
