Metadata-Version: 2.1
Name: omfvtk
Version: 0.0.0
Summary: A VTK interface for the Open Mining Format package
Home-page: https://github.com/OpenGeoVis/omfvtk
Author: Bane Sullivan
Author-email: info@pvgeo.org
License: UNKNOWN
Platform: UNKNOWN
Classifier: Programming Language :: Python
Classifier: License :: OSI Approved :: BSD License
Classifier: Operating System :: OS Independent
Classifier: Natural Language :: English
Requires-Dist: omf (>=0.9.3)
Requires-Dist: vectormath (>=0.2.0)
Requires-Dist: vtki (>=0.14.1)
Requires-Dist: numpy
Requires-Dist: vtk (>=8.1.0)
